main.py
glacify/__init__.py
glacify/base.py
glacify/column.py
glacify/exceptions.py
glacify/meta.py
glacify/settings.py
glacify/types.py
glacify/wrappers.py
glacify/setters/__init__.py
glacify/setters/general.py
glacify/setters/temporal.py
glacify/validators/__init__.py
glacify/validators/general.py
glacify/validators/numeric.py
glacify/validators/string.py
glacify/validators/temporal.py
glacify-0.2.0.dist-info/LICENSE
glacify-0.2.0.dist-info/METADATA
glacify-0.2.0.dist-info/WHEEL
glacify-0.2.0.dist-info/top_level.txt
glacify-0.2.0.dist-info/RECORD
